bw/pp.py
bw/bl/add_text.py
bw/bl/assign_color.py
bw/bl/assign_material.py
bw/bl/clear_all_objects.py
bw/bl/colors.py
bw/bl/create_rectangle.py
bw/bl/decimator_on_active_object.py
bw/bl/decimator_on_object.py
bw/bl/draw_model_layers.py
bw/bl/generate_3d_from_3d.py
bw/bl/get_quantile_colors.py
bw/bl/render_animation.py
bw/bl/run_ai_training_visualizer.py
bw/bl/save_animation.py
bw/bl/save_as_gltf.py
bw/bl/save_as_stl.py
bw/bl/set_animation_parameters.py
bw/bl/set_background_color.py
bw/bl/set_camera_location_orientation.py
bw/bl/set_output_file.py
bw/bl/set_render_settings.py
bw/converter/convert_tensor_weights_to_tiff.py
bw/diff/generators.py
bw/np/calculate_weighted_quantile_ranges_2d.py
bw/np/calculate_weighted_quantile_ranges_3d.py
bw/np/create_random_2d_arrays.py
bw/np/downscale_2d_array.py
bw/np/extract_weights.py
bw/np/fit_2d_array_to_target_shape.py
bw/np/fit_2d_arrays_to_target_shape.py
bw/np/upscale_2d_array.py
bw/sk/profile_data_with_cubes.py
bw/st/extract.py
bw/st/extract_3d_shapes_from_model_file.py
bw/st/get_model_tensors.py
bampe_weights-0.1.0.dist-info/METADATA
bampe_weights-0.1.0.dist-info/WHEEL
bampe_weights-0.1.0.dist-info/top_level.txt
bampe_weights-0.1.0.dist-info/RECORD
