Metadata-Version: 2.1
Name: bampe-weights
Version: 0.1.0
Summary: An alternative approach to building foundational generative AI models with visualizations using Blender
Home-page: https://github.com/matlok-ai/bampe-weights
Author: matlok-ops
Author-email: hello@matlok.ai
License: MIT
Keywords: artificial intelligence,deep learning,transformers
Platform: UNKNOWN
Classifier: Development Status :: 4 - Beta
Classifier: Intended Audience :: Developers
Classifier: Topic :: Scientific/Engineering :: Artificial Intelligence
Classifier: License :: OSI Approved :: MIT License
Classifier: Programming Language :: Python :: 3.10
Classifier: Programming Language :: Python :: 3.11
Requires-Dist: Pillow
Requires-Dist: black
Requires-Dist: diffusers[torch]
Requires-Dist: flake8
Requires-Dist: numpy
Requires-Dist: pycodestyle
Requires-Dist: safetensors
Requires-Dist: torch
Requires-Dist: transformers
